{
  "palette": {
    "x": 8,
    "y": 112,
    "width": 304,
    "height": 684,
    "top": 112,
    "bottom": 796,
    "left": 8,
    "right": 312
  },
  "body": {
    "x": 9,
    "y": 209,
    "width": 302,
    "height": 414,
    "top": 209,
    "bottom": 623,
    "left": 9,
    "right": 311
  },
  "overview": {
    "x": 19,
    "y": 623,
    "width": 282,
    "height": 160,
    "top": 623,
    "bottom": 783,
    "left": 19,
    "right": 301
  },
  "bodyScrollTop": 0,
  "bodyClientHeight": 414,
  "bodyScrollHeight": 420,
  "bodyNeedsScroll": true,
  "bodyOverviewGap": 0,
  "categories": [
    {
      "heading": "Energy",
      "rect": {
        "x": 19,
        "y": 246,
        "width": 282,
        "height": 130,
        "top": 246,
        "bottom": 376,
        "left": 19,
        "right": 301
      },
      "visibleInsideBody": true
    },
    {
      "heading": "Datacenters",
      "rect": {
        "x": 19,
        "y": 381,
        "width": 282,
        "height": 77,
        "top": 381,
        "bottom": 458,
        "left": 19,
        "right": 301
      },
      "visibleInsideBody": true
    },
    {
      "heading": "Cooling",
      "rect": {
        "x": 19,
        "y": 463,
        "width": 282,
        "height": 77,
        "top": 463,
        "bottom": 540,
        "left": 19,
        "right": 301
      },
      "visibleInsideBody": true
    },
    {
      "heading": "Research",
      "rect": {
        "x": 19,
        "y": 545,
        "width": 282,
        "height": 76,
        "top": 545,
        "bottom": 621,
        "left": 19,
        "right": 301
      },
      "visibleInsideBody": true
    }
  ],
  "gridNetworkVisible": false,
  "visibleText": "Fermer Construction Recherche Afficher verrouilles All 10 Energy 4 Datacenters 1 Cooling 2 Research 3 Grid & Network 0 Energy Centrale gaz 180M · 4m · 2 slots +25 E+8 CO2 Centrale nucléaire 900M · 24m · 4 slots +90 E-4 F+0 CO2 Éolien terrestre 140M · 6m · 1 slots +14 E Solaire 110M · 5m · 1 slots +12 E Datacenters Datacenter standard 300M · 6m · 2 slots +10 C-12 E-10 F Cooling Refroidissement air 90M · 3m · 1 slots +12 F-4 E Refroidissement marin 220M · 8m · 1 slots +40 F-3 E Research Université 120M · 4m · 1 slots +8 R&D-2 E AGI+ Centre recherche IA 220M · 8m · 2 slots -8 E Paliers Centre recherche énergie 220M · 8m · 2 slots -6 E Grid overview [] Power flow 23 Data flow 10 Congestion 4 Planned"
}