{
  "states": [
    {
      "name": "concept-overview",
      "width": 368,
      "height": 684,
      "overflowY": 0,
      "activeTabs": [
        "Overview"
      ],
      "builtCards": 10,
      "queueCards": 0,
      "statusBlocks": 3,
      "emptyCards": 2
    },
    {
      "name": "real-overview",
      "width": 368,
      "height": 684,
      "overflowY": 0,
      "activeTabs": [
        "Overview"
      ],
      "builtCards": 0,
      "queueCards": 0,
      "statusBlocks": 3,
      "emptyCards": 3
    }
  ]
}